jupyterlab_voiceatlas/__init__.py
jupyterlab_voiceatlas/_version.py
jupyterlab_voiceatlas/handlers.py
jupyterlab_voiceatlas/labextension/build_log.json
jupyterlab_voiceatlas/labextension/install.json
jupyterlab_voiceatlas/labextension/package.json
jupyterlab_voiceatlas/labextension/schemas/jupyterlab_voiceatlas/package.json.orig
jupyterlab_voiceatlas/labextension/schemas/jupyterlab_voiceatlas/plugin.json
jupyterlab_voiceatlas/labextension/static/lib_index_js.9568c4c45c4e4bb914f0.js
jupyterlab_voiceatlas/labextension/static/lib_index_js.9568c4c45c4e4bb914f0.js.map
jupyterlab_voiceatlas/labextension/static/remoteEntry.766497d5acf3f183b760.js
jupyterlab_voiceatlas/labextension/static/remoteEntry.766497d5acf3f183b760.js.map
jupyterlab_voiceatlas/labextension/static/style.js
jupyterlab_voiceatlas/labextension/static/style_index_css.3dc010fcea6a1be8fcd7.js
jupyterlab_voiceatlas/labextension/static/style_index_css.3dc010fcea6a1be8fcd7.js.map
jupyterlab_voiceatlas/labextension/static/vendors-node_modules_css-loader_dist_runtime_api_js-node_modules_css-loader_dist_runtime_cssW-72eba1.b97e434cd56da264030e.js
jupyterlab_voiceatlas/labextension/static/vendors-node_modules_css-loader_dist_runtime_api_js-node_modules_css-loader_dist_runtime_cssW-72eba1.b97e434cd56da264030e.js.map
jupyterlab_voiceatlas/labextension/static/vendors-node_modules_jupyterlab_toastify_lib_index_js.adfbac397ad46008b7ab.js
jupyterlab_voiceatlas/labextension/static/vendors-node_modules_jupyterlab_toastify_lib_index_js.adfbac397ad46008b7ab.js.map
jupyterlab_voiceatlas/labextension/static/vendors-node_modules_lodash_isempty_index_js.a8ee7ea9325597c9aff4.js
jupyterlab_voiceatlas/labextension/static/vendors-node_modules_lodash_isempty_index_js.a8ee7ea9325597c9aff4.js.map
jupyterlab_voiceatlas/labextension/static/vendors-node_modules_lodash_isequal_index_js.25147cec73a51ddc5539.js
jupyterlab_voiceatlas/labextension/static/vendors-node_modules_lodash_isequal_index_js.25147cec73a51ddc5539.js.map
jupyterlab_voiceatlas-0.1.4.dist-info/METADATA
jupyterlab_voiceatlas-0.1.4.dist-info/WHEEL
jupyterlab_voiceatlas-0.1.4.dist-info/licenses/LICENSE
jupyterlab_voiceatlas-0.1.4.dist-info/RECORD
