Metadata-Version: 2.1
Name: jupyterlab_voiceatlas
Version: 0.1.4
Summary: A JupyterLab Extension for Voice Atlas.
Project-URL: Homepage, https://github.com/Navteca/jupyterlab-voice-atlas
Project-URL: Bug Tracker, https://github.com/Navteca/jupyterlab-voice-atlas/issues
Project-URL: Repository, https://github.com/navteca/jupyterlab_voiceatlas.git
Author-email: Navteca LLC <info@navteca.com>
License: BSD 3-Clause License
License-File: LICENSE
Classifier: Framework :: Jupyter
Classifier: Framework :: Jupyter :: JupyterLab
Classifier: Framework :: Jupyter :: JupyterLab :: 3
Classifier: Framework :: Jupyter :: JupyterLab :: Extensions
Classifier: Framework :: Jupyter :: JupyterLab :: Extensions :: Prebuilt
Classifier: License :: OSI Approved :: BSD License
Classifier: Programming Language :: Python
Classifier: Programming Language :: Python :: 3
Classifier: Programming Language :: Python :: 3.7
Classifier: Programming Language :: Python :: 3.8
Classifier: Programming Language :: Python :: 3.9
Classifier: Programming Language :: Python :: 3.10
Requires-Python: >=3.7
Requires-Dist: jupyter-server<3,>=2.0.1
Requires-Dist: nbformat
Provides-Extra: test
Requires-Dist: coverage; extra == 'test'
Requires-Dist: pytest; extra == 'test'
Requires-Dist: pytest-asyncio; extra == 'test'
Requires-Dist: pytest-cov; extra == 'test'
Requires-Dist: pytest-tornasync; extra == 'test'
